dora_lakehouse/__init__.py
dora_lakehouse/sdk/__init__.py
dora_lakehouse/sdk/aws/catalog.py
dora_lakehouse/sdk/aws/context.py
dora_lakehouse/sdk/catalog.py
dora_lakehouse/sdk/context.py
dora_lakehouse/sdk/datatable.py
dora_lakehouse_sdk-0.0.2.dist-info/LICENSE
dora_lakehouse_sdk-0.0.2.dist-info/WHEEL
dora_lakehouse_sdk-0.0.2.dist-info/METADATA
dora_lakehouse_sdk-0.0.2.dist-info/RECORD
