Metadata-Version: 2.1
Name: dora-lakehouse-sdk
Version: 0.0.2
Summary: Dora Lakehouse
Home-page: https://github.com/doraproject/lakehouse
License: Apache-2.0
Keywords: dora,lakehouse
Author: Didone
Author-email: didone@live.com
Maintainer: DataLabs
Maintainer-email: time.dataanalytics.datalabs@compasso.com.br
Requires-Python: >=3.7,<4.0
Classifier: Development Status :: 4 - Beta
Classifier: License :: OSI Approved :: Apache Software License
Classifier: Programming Language :: Python :: 3
Classifier: Programming Language :: Python :: 3.7
Classifier: Programming Language :: Python :: 3.8
Classifier: Programming Language :: Python :: 3.9
Classifier: Topic :: Software Development :: Libraries
Classifier: Topic :: Software Development :: Libraries :: Python Modules
Project-URL: Bug Tracker, https://github.com/doraproject/lakehouse-sdk/issues
Project-URL: Repository, https://github.com/doraproject/lakehouse-sdk.git
